AUTHORS
ChangeLog
README
requirements.txt
setup.cfg
setup.py
keefind/__init__.py
keefind/keefinder.py
keefind/kf.py
keefind.egg-info/PKG-INFO
keefind.egg-info/SOURCES.txt
keefind.egg-info/dependency_links.txt
keefind.egg-info/entry_points.txt
keefind.egg-info/not-zip-safe
keefind.egg-info/pbr.json
keefind.egg-info/requires.txt
keefind.egg-info/top_level.txt