Metadata-Version: 1.1
Name: keefind
Version: 0.1.0
Summary: Utility to easy find in keepass database
Home-page: UNKNOWN
Author: Stanislaw Bogatkin
Author-email: sbog@sbog.ru
License: UNKNOWN
Platform: UNKNOWN
Classifier: Intended Audience :: Information Technology
Classifier: Intended Audience :: System Administrators
Classifier: License :: OSI Approved :: Apache Software License
Classifier: Operating System :: POSIX :: Linux
Classifier: Programming Language :: Python
Classifier: Programming Language :: Python :: 3
